Metadata-Version: 1.1
Name: django-nofloc
Version: 0.2
Summary: Opt out of the privacy invading Google FLoC program.
Home-page: https://hg.code.netlandish.com/~netlandish/django-nofloc
Author: Netlandish Inc.
Author-email: hello@netlandish.com
License: BSD License
Platform: any
Classifier: Development Status :: 4 - Beta
Classifier: Intended Audience :: Developers
Classifier: License :: OSI Approved :: BSD License
Classifier: Natural Language :: English
Classifier: Operating System :: OS Independent
Classifier: Programming Language :: Python
Classifier: Environment :: Web Environment
Classifier: Programming Language :: Python
Classifier: Programming Language :: Python :: 3 :: Only
Classifier: Programming Language :: Python :: 3.6
Classifier: Programming Language :: Python :: 3.7
Classifier: Programming Language :: Python :: 3.8
